nucleotide/__init__.py
nucleotide/atom.py
nucleotide/catalog.py
nucleotide/config.py
nucleotide/custom.py
nucleotide/environment.py
nucleotide/klass.py
nucleotide/main.py
nucleotide/options.py
nucleotide/settings.py
nucleotide/translator.py
nucleotide/component/__init__.py
nucleotide/component/constant.py
nucleotide/component/function.py
nucleotide/component/main.py
nucleotide/component/translator.py
nucleotide/component/_common/__init__.py
nucleotide/component/_common/architecture.py
nucleotide/component/_common/blank.py
nucleotide/component/_common/boost.py
nucleotide/component/_common/include.py
nucleotide/component/_common/library.py
nucleotide/component/_common/package-model.py
nucleotide/component/_common/translator.py
nucleotide/component/_common/warning/__init__.py
nucleotide/component/_common/warning/table.py
nucleotide/component/_common/warning/util.py
nucleotide/component/linux/__init__.py
nucleotide/component/linux/translator.py
nucleotide/component/linux/_common/__init__.py
nucleotide/component/linux/_common/boost.py
nucleotide/component/linux/_common/translator.py
nucleotide/component/linux/gcc/__init__.py
nucleotide/component/linux/gcc/translator.py
nucleotide/component/linux/gcc/atom/__init__.py
nucleotide/component/linux/gcc/atom/_misc.py
nucleotide/component/linux/gcc/atom/alignment.py
nucleotide/component/linux/gcc/atom/blank.py
nucleotide/component/linux/gcc/atom/boost.py
nucleotide/component/linux/gcc/atom/configuration.py
nucleotide/component/linux/gcc/atom/dialect.py
nucleotide/component/linux/gcc/atom/encode.py
nucleotide/component/linux/gcc/atom/exception.py
nucleotide/component/linux/gcc/atom/executable.py
nucleotide/component/linux/gcc/atom/library.py
nucleotide/component/linux/gcc/atom/macro.py
nucleotide/component/linux/gcc/atom/optimization.py
nucleotide/component/linux/gcc/atom/package.py
nucleotide/component/linux/gcc/atom/pdb.py
nucleotide/component/linux/gcc/atom/pp2f.py
nucleotide-0.1.4.8.dist-info/METADATA
nucleotide-0.1.4.8.dist-info/RECORD
nucleotide-0.1.4.8.dist-info/WHEEL
nucleotide-0.1.4.8.dist-info/top_level.txt
