Metadata-Version: 2.1
Name: nucleotide
Version: 0.1.4.8
Summary: An Scons library which wraps interface of various compilers in to one universal.
Home-page: https://github.com/dmilos/nucleotide
Author: Dejan Milosavljevic
Author-email: dmilos@gmail.com
License: https://raw.githubusercontent.com/dmilos/nucleotide/master/license.txt
Keywords: scons,module,universal,unified,compiler,c++
Platform: All
Classifier: Development Status :: 3 - Alpha
Classifier: Programming Language :: Python :: 2.7
Classifier: Programming Language :: Python :: 3
Classifier: Intended Audience :: Developers
Classifier: Operating System :: OS Independent
Classifier: License :: OSI Approved :: Apache Software License
Classifier: Topic :: Software Development :: Build Tools
